markdown_importer/__init__.py
markdown_importer/__main__.py
markdown_importer-1.0.1.dist-info/METADATA
markdown_importer-1.0.1.dist-info/WHEEL
markdown_importer-1.0.1.dist-info/entry_points.txt
markdown_importer-1.0.1.dist-info/top_level.txt
markdown_importer-1.0.1.dist-info/RECORD
