Metadata-Version: 2.1
Name: markdown-importer
Version: 1.0.1
Summary: Markdown dosyalarını modüler bir şekilde yönetmenizi sağlayan araç
Home-page: https://github.com/VirtualExecutive/Markdown-Importer
Author: VirtualExecutive
Author-email: VirtualExecutive <your.email@example.com>
Project-URL: Homepage, https://github.com/VirtualExecutive/Markdown-Importer
Project-URL: Issues, https://github.com/VirtualExecutive/Markdown-Importer/issues
Classifier: Programming Language :: Python :: 3
Classifier: License :: OSI Approved :: MIT License
Classifier: Operating System :: OS Independent
Requires-Python: >=3.6
